setup.cfg
setup.py
bin/git-archive
git_archive/__init__.py
git_archive/git_archive.py
git_archive.egg-info/PKG-INFO
git_archive.egg-info/SOURCES.txt
git_archive.egg-info/dependency_links.txt
git_archive.egg-info/top_level.txt