Metadata-Version: 1.0
Name: git-archive
Version: 0.3.0
Summary: Go back into the git archive
Home-page: https://github.com/EricChiang/git-archive
Author: Eric Chiang
Author-email: eric@yhathq.com
License: MIT
Platform: UNKNOWN
